pamila/__init__.py
pamila-0.0.0.dist-info/LICENSE
pamila-0.0.0.dist-info/METADATA
pamila-0.0.0.dist-info/WHEEL
pamila-0.0.0.dist-info/RECORD
